cli/__init__.py
cli/parser.py
cli/types.py
cli/util.py
cli/commands/__init__.py
cli/commands/list.py
cli/commands/logs.py
cli/commands/status.py
cli/commands/stop.py
cli/commands/submit.py
jobq/__init__.py
jobq/execute.py
jobq/image.py
jobq/job.py
jobq/py.typed
jobq/submission_context.py
jobq/types.py
jobq/assembler/__init__.py
jobq/assembler/config.py
jobq/assembler/renderers.py
jobq/utils/__init__.py
jobq/utils/helpers.py
jobq/utils/math.py
jobq/utils/processes.py
openapi_client/__init__.py
openapi_client/api_client.py
openapi_client/api_response.py
openapi_client/configuration.py
openapi_client/exceptions.py
openapi_client/rest.py
openapi_client/api/__init__.py
openapi_client/api/job_management_api.py
openapi_client/models/__init__.py
openapi_client/models/create_job_model.py
openapi_client/models/execution_mode.py
openapi_client/models/http_validation_error.py
openapi_client/models/job_options.py
openapi_client/models/job_status.py
openapi_client/models/list_workload_model.py
openapi_client/models/resource_options.py
openapi_client/models/scheduling_options.py
openapi_client/models/validation_error.py
openapi_client/models/validation_error_loc_inner.py
openapi_client/models/workload_admission.py
openapi_client/models/workload_identifier.py
openapi_client/models/workload_metadata.py
openapi_client/models/workload_spec.py
openapi_client/models/workload_status.py
aai_jobq-0.1.0rc9.dist-info/METADATA
aai_jobq-0.1.0rc9.dist-info/WHEEL
aai_jobq-0.1.0rc9.dist-info/entry_points.txt
aai_jobq-0.1.0rc9.dist-info/top_level.txt
aai_jobq-0.1.0rc9.dist-info/RECORD
