Metadata-Version: 2.1
Name: aai-jobq
Version: 0.1.0rc9
Author-email: appliedAI Institute for Europe <opensource@appliedai-institute.de>
Maintainer-email: Nicholas Junge <n.junge@appliedai-institute.de>, Max Mynter <m.mynter@appliedai-institute.de>, Adrian Rumpold <a.rumpold@appliedai-institute.de>
License: Apache-2.0
Requires-Python: >=3.10
Requires-Dist: pydantic
Requires-Dist: pyyaml
Provides-Extra: cli
Requires-Dist: docker; extra == "cli"
Requires-Dist: humanize; extra == "cli"
Requires-Dist: rich; extra == "cli"
Requires-Dist: pydantic-settings; extra == "cli"
Requires-Dist: python-dateutil; extra == "cli"
Provides-Extra: dev
Requires-Dist: build; extra == "dev"
Requires-Dist: ruff; extra == "dev"
Requires-Dist: pytest; extra == "dev"
Requires-Dist: pytest-cov; extra == "dev"
Requires-Dist: pre-commit; extra == "dev"
Requires-Dist: click; extra == "dev"
